<annotation>
	<folder>my-project-name</folder>
	<filename>5071.jpg</filename>
	<path>/my-project-name/5071.jpg</path>
	<source>
		<database>Unspecified</database>
	</source>
	<size>
		<width>1920</width>
		<height>1080</height>
		<depth>3</depth>
	</size>
	<object>
		<name>Drinking</name>
		<pose>Unspecified</pose>
		<truncated>0</truncated>
		<difficult>0</difficult>
		<bndbox>
			<xmin>1099</xmin>
			<ymin>480</ymin>
			<xmax>1268</xmax>
			<ymax>571</ymax>
		</bndbox>
	</object>
	<object>
		<name>Drinking</name>
		<pose>Unspecified</pose>
		<truncated>0</truncated>
		<difficult>0</difficult>
		<bndbox>
			<xmin>974</xmin>
			<ymin>430</ymin>
			<xmax>1121</xmax>
			<ymax>573</ymax>
		</bndbox>
	</object>
	<object>
		<name>Pecking</name>
		<pose>Unspecified</pose>
		<truncated>0</truncated>
		<difficult>0</difficult>
		<bndbox>
			<xmin>983</xmin>
			<ymin>761</ymin>
			<xmax>1107</xmax>
			<ymax>956</ymax>
		</bndbox>
	</object>
	<object>
		<name>Perching</name>
		<pose>Unspecified</pose>
		<truncated>0</truncated>
		<difficult>0</difficult>
		<bndbox>
			<xmin>435</xmin>
			<ymin>774</ymin>
			<xmax>654</xmax>
			<ymax>898</ymax>
		</bndbox>
	</object>
	<object>
		<name>Perching</name>
		<pose>Unspecified</pose>
		<truncated>0</truncated>
		<difficult>0</difficult>
		<bndbox>
			<xmin>503</xmin>
			<ymin>662</ymin>
			<xmax>621</xmax>
			<ymax>745</ymax>
		</bndbox>
	</object>
	<object>
		<name>Perching</name>
		<pose>Unspecified</pose>
		<truncated>0</truncated>
		<difficult>0</difficult>
		<bndbox>
			<xmin>281</xmin>
			<ymin>712</ymin>
			<xmax>405</xmax>
			<ymax>908</ymax>
		</bndbox>
	</object>
	<object>
		<name>Perching</name>
		<pose>Unspecified</pose>
		<truncated>0</truncated>
		<difficult>0</difficult>
		<bndbox>
			<xmin>116</xmin>
			<ymin>855</ymin>
			<xmax>234</xmax>
			<ymax>1026</ymax>
		</bndbox>
	</object>
	<object>
		<name>Perching</name>
		<pose>Unspecified</pose>
		<truncated>0</truncated>
		<difficult>0</difficult>
		<bndbox>
			<xmin>134</xmin>
			<ymin>745</ymin>
			<xmax>246</xmax>
			<ymax>883</ymax>
		</bndbox>
	</object>
	<object>
		<name>Perching</name>
		<pose>Unspecified</pose>
		<truncated>0</truncated>
		<difficult>0</difficult>
		<bndbox>
			<xmin>143</xmin>
			<ymin>646</ymin>
			<xmax>255</xmax>
			<ymax>792</ymax>
		</bndbox>
	</object>
	<object>
		<name>Perching</name>
		<pose>Unspecified</pose>
		<truncated>0</truncated>
		<difficult>0</difficult>
		<bndbox>
			<xmin>105</xmin>
			<ymin>610</ymin>
			<xmax>143</xmax>
			<ymax>710</ymax>
		</bndbox>
	</object>
	<object>
		<name>Perching</name>
		<pose>Unspecified</pose>
		<truncated>0</truncated>
		<difficult>0</difficult>
		<bndbox>
			<xmin>19</xmin>
			<ymin>706</ymin>
			<xmax>155</xmax>
			<ymax>885</ymax>
		</bndbox>
	</object>
	<object>
		<name>Perching</name>
		<pose>Unspecified</pose>
		<truncated>0</truncated>
		<difficult>0</difficult>
		<bndbox>
			<xmin>0</xmin>
			<ymin>937</ymin>
			<xmax>130</xmax>
			<ymax>1076</ymax>
		</bndbox>
	</object>
	<object>
		<name>Perching</name>
		<pose>Unspecified</pose>
		<truncated>0</truncated>
		<difficult>0</difficult>
		<bndbox>
			<xmin>267</xmin>
			<ymin>623</ymin>
			<xmax>375</xmax>
			<ymax>732</ymax>
		</bndbox>
	</object>
	<object>
		<name>Pecking</name>
		<pose>Unspecified</pose>
		<truncated>0</truncated>
		<difficult>0</difficult>
		<bndbox>
			<xmin>405</xmin>
			<ymin>141</ymin>
			<xmax>495</xmax>
			<ymax>290</ymax>
		</bndbox>
	</object>
</annotation>