<annotation>
	<folder>my-project-name</folder>
	<filename>5220.jpg</filename>
	<path>/my-project-name/5220.jpg</path>
	<source>
		<database>Unspecified</database>
	</source>
	<size>
		<width>1920</width>
		<height>1080</height>
		<depth>3</depth>
	</size>
	<object>
		<name>Drinking</name>
		<pose>Unspecified</pose>
		<truncated>0</truncated>
		<difficult>0</difficult>
		<bndbox>
			<xmin>778</xmin>
			<ymin>197</ymin>
			<xmax>954</xmax>
			<ymax>273</ymax>
		</bndbox>
	</object>
	<object>
		<name>Drinking</name>
		<pose>Unspecified</pose>
		<truncated>0</truncated>
		<difficult>0</difficult>
		<bndbox>
			<xmin>757</xmin>
			<ymin>325</ymin>
			<xmax>929</xmax>
			<ymax>430</ymax>
		</bndbox>
	</object>
	<object>
		<name>Drinking</name>
		<pose>Unspecified</pose>
		<truncated>0</truncated>
		<difficult>0</difficult>
		<bndbox>
			<xmin>885</xmin>
			<ymin>441</ymin>
			<xmax>1084</xmax>
			<ymax>523</ymax>
		</bndbox>
	</object>
	<object>
		<name>Drinking</name>
		<pose>Unspecified</pose>
		<truncated>0</truncated>
		<difficult>0</difficult>
		<bndbox>
			<xmin>747</xmin>
			<ymin>451</ymin>
			<xmax>908</xmax>
			<ymax>563</ymax>
		</bndbox>
	</object>
	<object>
		<name>Pecking</name>
		<pose>Unspecified</pose>
		<truncated>0</truncated>
		<difficult>0</difficult>
		<bndbox>
			<xmin>759</xmin>
			<ymin>569</ymin>
			<xmax>888</xmax>
			<ymax>679</ymax>
		</bndbox>
	</object>
	<object>
		<name>Dust Bathing</name>
		<pose>Unspecified</pose>
		<truncated>0</truncated>
		<difficult>0</difficult>
		<bndbox>
			<xmin>871</xmin>
			<ymin>786</ymin>
			<xmax>946</xmax>
			<ymax>964</ymax>
		</bndbox>
	</object>
	<object>
		<name>Foraging</name>
		<pose>Unspecified</pose>
		<truncated>0</truncated>
		<difficult>0</difficult>
		<bndbox>
			<xmin>1154</xmin>
			<ymin>207</ymin>
			<xmax>1343</xmax>
			<ymax>343</ymax>
		</bndbox>
	</object>
	<object>
		<name>Foraging</name>
		<pose>Unspecified</pose>
		<truncated>0</truncated>
		<difficult>0</difficult>
		<bndbox>
			<xmin>1214</xmin>
			<ymin>778</ymin>
			<xmax>1289</xmax>
			<ymax>989</ymax>
		</bndbox>
	</object>
	<object>
		<name>Foraging</name>
		<pose>Unspecified</pose>
		<truncated>0</truncated>
		<difficult>0</difficult>
		<bndbox>
			<xmin>1239</xmin>
			<ymin>962</ymin>
			<xmax>1341</xmax>
			<ymax>1080</ymax>
		</bndbox>
	</object>
	<object>
		<name>Feeding</name>
		<pose>Unspecified</pose>
		<truncated>0</truncated>
		<difficult>0</difficult>
		<bndbox>
			<xmin>1227</xmin>
			<ymin>403</ymin>
			<xmax>1392</xmax>
			<ymax>596</ymax>
		</bndbox>
	</object>
	<object>
		<name>Feeding</name>
		<pose>Unspecified</pose>
		<truncated>0</truncated>
		<difficult>0</difficult>
		<bndbox>
			<xmin>317</xmin>
			<ymin>960</ymin>
			<xmax>443</xmax>
			<ymax>1061</ymax>
		</bndbox>
	</object>
	<object>
		<name>Perching</name>
		<pose>Unspecified</pose>
		<truncated>0</truncated>
		<difficult>0</difficult>
		<bndbox>
			<xmin>23</xmin>
			<ymin>621</ymin>
			<xmax>97</xmax>
			<ymax>805</ymax>
		</bndbox>
	</object>
	<object>
		<name>Perching</name>
		<pose>Unspecified</pose>
		<truncated>0</truncated>
		<difficult>0</difficult>
		<bndbox>
			<xmin>126</xmin>
			<ymin>708</ymin>
			<xmax>207</xmax>
			<ymax>877</ymax>
		</bndbox>
	</object>
	<object>
		<name>Perching</name>
		<pose>Unspecified</pose>
		<truncated>0</truncated>
		<difficult>0</difficult>
		<bndbox>
			<xmin>205</xmin>
			<ymin>650</ymin>
			<xmax>269</xmax>
			<ymax>881</ymax>
		</bndbox>
	</object>
	<object>
		<name>Perching</name>
		<pose>Unspecified</pose>
		<truncated>0</truncated>
		<difficult>0</difficult>
		<bndbox>
			<xmin>0</xmin>
			<ymin>8</ymin>
			<xmax>101</xmax>
			<ymax>203</ymax>
		</bndbox>
	</object>
	<object>
		<name>Perching</name>
		<pose>Unspecified</pose>
		<truncated>0</truncated>
		<difficult>0</difficult>
		<bndbox>
			<xmin>168</xmin>
			<ymin>8</ymin>
			<xmax>259</xmax>
			<ymax>105</ymax>
		</bndbox>
	</object>
	<object>
		<name>Preening</name>
		<pose>Unspecified</pose>
		<truncated>0</truncated>
		<difficult>0</difficult>
		<bndbox>
			<xmin>567</xmin>
			<ymin>523</ymin>
			<xmax>716</xmax>
			<ymax>668</ymax>
		</bndbox>
	</object>
	<object>
		<name>Preening</name>
		<pose>Unspecified</pose>
		<truncated>0</truncated>
		<difficult>0</difficult>
		<bndbox>
			<xmin>466</xmin>
			<ymin>292</ymin>
			<xmax>557</xmax>
			<ymax>474</ymax>
		</bndbox>
	</object>
	<object>
		<name>Foraging</name>
		<pose>Unspecified</pose>
		<truncated>0</truncated>
		<difficult>0</difficult>
		<bndbox>
			<xmin>443</xmin>
			<ymin>201</ymin>
			<xmax>586</xmax>
			<ymax>312</ymax>
		</bndbox>
	</object>
	<object>
		<name>Foraging</name>
		<pose>Unspecified</pose>
		<truncated>0</truncated>
		<difficult>0</difficult>
		<bndbox>
			<xmin>1136</xmin>
			<ymin>617</ymin>
			<xmax>1320</xmax>
			<ymax>724</ymax>
		</bndbox>
	</object>
</annotation>