<annotation>
	<folder>my-project-name</folder>
	<filename>5392.jpg</filename>
	<path>/my-project-name/5392.jpg</path>
	<source>
		<database>Unspecified</database>
	</source>
	<size>
		<width>1920</width>
		<height>1080</height>
		<depth>3</depth>
	</size>
	<object>
		<name>Feeding</name>
		<pose>Unspecified</pose>
		<truncated>0</truncated>
		<difficult>0</difficult>
		<bndbox>
			<xmin>234</xmin>
			<ymin>364</ymin>
			<xmax>406</xmax>
			<ymax>432</ymax>
		</bndbox>
	</object>
	<object>
		<name>Feeding</name>
		<pose>Unspecified</pose>
		<truncated>0</truncated>
		<difficult>0</difficult>
		<bndbox>
			<xmin>478</xmin>
			<ymin>232</ymin>
			<xmax>693</xmax>
			<ymax>323</ymax>
		</bndbox>
	</object>
	<object>
		<name>Feeding</name>
		<pose>Unspecified</pose>
		<truncated>0</truncated>
		<difficult>0</difficult>
		<bndbox>
			<xmin>414</xmin>
			<ymin>348</ymin>
			<xmax>494</xmax>
			<ymax>569</ymax>
		</bndbox>
	</object>
	<object>
		<name>Feeding</name>
		<pose>Unspecified</pose>
		<truncated>0</truncated>
		<difficult>0</difficult>
		<bndbox>
			<xmin>1339</xmin>
			<ymin>327</ymin>
			<xmax>1570</xmax>
			<ymax>426</ymax>
		</bndbox>
	</object>
	<object>
		<name>Preening</name>
		<pose>Unspecified</pose>
		<truncated>0</truncated>
		<difficult>0</difficult>
		<bndbox>
			<xmin>768</xmin>
			<ymin>408</ymin>
			<xmax>987</xmax>
			<ymax>517</ymax>
		</bndbox>
	</object>
	<object>
		<name>Preening</name>
		<pose>Unspecified</pose>
		<truncated>0</truncated>
		<difficult>0</difficult>
		<bndbox>
			<xmin>662</xmin>
			<ymin>724</ymin>
			<xmax>759</xmax>
			<ymax>933</ymax>
		</bndbox>
	</object>
	<object>
		<name>Perching</name>
		<pose>Unspecified</pose>
		<truncated>0</truncated>
		<difficult>0</difficult>
		<bndbox>
			<xmin>211</xmin>
			<ymin>497</ymin>
			<xmax>306</xmax>
			<ymax>716</ymax>
		</bndbox>
	</object>
	<object>
		<name>Foraging</name>
		<pose>Unspecified</pose>
		<truncated>0</truncated>
		<difficult>0</difficult>
		<bndbox>
			<xmin>1444</xmin>
			<ymin>766</ymin>
			<xmax>1566</xmax>
			<ymax>900</ymax>
		</bndbox>
	</object>
	<object>
		<name>Drinking</name>
		<pose>Unspecified</pose>
		<truncated>0</truncated>
		<difficult>0</difficult>
		<bndbox>
			<xmin>1068</xmin>
			<ymin>397</ymin>
			<xmax>1154</xmax>
			<ymax>530</ymax>
		</bndbox>
	</object>
	<object>
		<name>Drinking</name>
		<pose>Unspecified</pose>
		<truncated>0</truncated>
		<difficult>0</difficult>
		<bndbox>
			<xmin>1125</xmin>
			<ymin>348</ymin>
			<xmax>1237</xmax>
			<ymax>486</ymax>
		</bndbox>
	</object>
	<object>
		<name>Drinking</name>
		<pose>Unspecified</pose>
		<truncated>0</truncated>
		<difficult>0</difficult>
		<bndbox>
			<xmin>1078</xmin>
			<ymin>583</ymin>
			<xmax>1221</xmax>
			<ymax>699</ymax>
		</bndbox>
	</object>
	<object>
		<name>Drinking</name>
		<pose>Unspecified</pose>
		<truncated>0</truncated>
		<difficult>0</difficult>
		<bndbox>
			<xmin>917</xmin>
			<ymin>817</ymin>
			<xmax>1086</xmax>
			<ymax>933</ymax>
		</bndbox>
	</object>
	<object>
		<name>Drinking</name>
		<pose>Unspecified</pose>
		<truncated>0</truncated>
		<difficult>0</difficult>
		<bndbox>
			<xmin>885</xmin>
			<ymin>970</ymin>
			<xmax>1072</xmax>
			<ymax>1070</ymax>
		</bndbox>
	</object>
	<object>
		<name>Foraging</name>
		<pose>Unspecified</pose>
		<truncated>0</truncated>
		<difficult>0</difficult>
		<bndbox>
			<xmin>1603</xmin>
			<ymin>689</ymin>
			<xmax>1740</xmax>
			<ymax>778</ymax>
		</bndbox>
	</object>
	<object>
		<name>Foraging</name>
		<pose>Unspecified</pose>
		<truncated>0</truncated>
		<difficult>0</difficult>
		<bndbox>
			<xmin>1661</xmin>
			<ymin>821</ymin>
			<xmax>1769</xmax>
			<ymax>890</ymax>
		</bndbox>
	</object>
	<object>
		<name>Foraging</name>
		<pose>Unspecified</pose>
		<truncated>0</truncated>
		<difficult>0</difficult>
		<bndbox>
			<xmin>1678</xmin>
			<ymin>374</ymin>
			<xmax>1746</xmax>
			<ymax>459</ymax>
		</bndbox>
	</object>
</annotation>