<annotation>
	<folder>my-project-name</folder>
	<filename>3557.jpg</filename>
	<path>/my-project-name/3557.jpg</path>
	<source>
		<database>Unspecified</database>
	</source>
	<size>
		<width>1920</width>
		<height>1080</height>
		<depth>3</depth>
	</size>
	<object>
		<name>Feeding</name>
		<pose>Unspecified</pose>
		<truncated>Unspecified</truncated>
		<difficult>Unspecified</difficult>
		<bndbox>
			<xmin>809</xmin>
			<ymin>267</ymin>
			<xmax>995</xmax>
			<ymax>455</ymax>
		</bndbox>
	</object>
	<object>
		<name>Foraging</name>
		<pose>Unspecified</pose>
		<truncated>Unspecified</truncated>
		<difficult>Unspecified</difficult>
		<bndbox>
			<xmin>540</xmin>
			<ymin>416</ymin>
			<xmax>712</xmax>
			<ymax>623</ymax>
		</bndbox>
	</object>
	<object>
		<name>Foraging</name>
		<pose>Unspecified</pose>
		<truncated>Unspecified</truncated>
		<difficult>Unspecified</difficult>
		<bndbox>
			<xmin>1295</xmin>
			<ymin>41</ymin>
			<xmax>1403</xmax>
			<ymax>205</ymax>
		</bndbox>
	</object>
	<object>
		<name>Preening</name>
		<pose>Unspecified</pose>
		<truncated>Unspecified</truncated>
		<difficult>Unspecified</difficult>
		<bndbox>
			<xmin>1005</xmin>
			<ymin>784</ymin>
			<xmax>1198</xmax>
			<ymax>900</ymax>
		</bndbox>
	</object>
	<object>
		<name>Perching</name>
		<pose>Unspecified</pose>
		<truncated>Unspecified</truncated>
		<difficult>Unspecified</difficult>
		<bndbox>
			<xmin>1616</xmin>
			<ymin>165</ymin>
			<xmax>1732</xmax>
			<ymax>300</ymax>
		</bndbox>
	</object>
	<object>
		<name>Perching</name>
		<pose>Unspecified</pose>
		<truncated>Unspecified</truncated>
		<difficult>Unspecified</difficult>
		<bndbox>
			<xmin>1591</xmin>
			<ymin>317</ymin>
			<xmax>1736</xmax>
			<ymax>422</ymax>
		</bndbox>
	</object>
	<object>
		<name>Perching</name>
		<pose>Unspecified</pose>
		<truncated>Unspecified</truncated>
		<difficult>Unspecified</difficult>
		<bndbox>
			<xmin>1614</xmin>
			<ymin>600</ymin>
			<xmax>1726</xmax>
			<ymax>745</ymax>
		</bndbox>
	</object>
	<object>
		<name>Perching</name>
		<pose>Unspecified</pose>
		<truncated>Unspecified</truncated>
		<difficult>Unspecified</difficult>
		<bndbox>
			<xmin>1740</xmin>
			<ymin>681</ymin>
			<xmax>1848</xmax>
			<ymax>790</ymax>
		</bndbox>
	</object>
	<object>
		<name>Perching</name>
		<pose>Unspecified</pose>
		<truncated>Unspecified</truncated>
		<difficult>Unspecified</difficult>
		<bndbox>
			<xmin>1603</xmin>
			<ymin>855</ymin>
			<xmax>1719</xmax>
			<ymax>952</ymax>
		</bndbox>
	</object>
</annotation>